redisbloomfilter/__init__.py
redisbloomfilter/bloomfilter.py
redisbloomfilter/exceptions.py
redis_bloom_filter-1.0.1.dist-info/LICENSE
redis_bloom_filter-1.0.1.dist-info/METADATA
redis_bloom_filter-1.0.1.dist-info/WHEEL
redis_bloom_filter-1.0.1.dist-info/top_level.txt
redis_bloom_filter-1.0.1.dist-info/RECORD
