Metadata-Version: 2.1
Name: redis-bloom-filter
Version: 1.0.1
Summary: Bloom filter based on redis
Home-page: https://github.com/anexplore/pyredisbloomfilter
Author: anexplore
Maintainer: anexplore
License: Apache
Keywords: bloom filter,redis bloom filter
Platform: UNKNOWN
Classifier: Programming Language :: Python
Classifier: Programming Language :: Python :: 2
Classifier: Programming Language :: Python :: 2.7
Classifier: Programming Language :: Python :: 3
Classifier: Programming Language :: Python :: 3.5
Classifier: Programming Language :: Python :: 3.6
Classifier: Programming Language :: Python :: 3.7
Classifier: Programming Language :: Python :: 3.8
Classifier: Environment :: Web Environment
Classifier: Operating System :: POSIX
Classifier: License :: OSI Approved :: Apache Software License
Requires-Python: >=2.7, !=3.0.*, !=3.1.*, !=3.2.*, !=3.3.*, !=3.4
Requires-Dist: redis (>=2.10.0)
Requires-Dist: mmh3 (>=2.5.0)
